[
    {
        "resource_state": 2,
        "athlete": {
            "id": 11730283,
            "resource_state": 1
        },
        "name": "🎿 🦭 Vercorin - Crêt du Midi ⛅️ 970 D+",
        "distance": 6285.1,
        "moving_time": 6404,
        "elapsed_time": 8004,
        "total_elevation_gain": 972.8,
        "type": "BackcountrySki",
        "sport_type": "BackcountrySki",
        "id": 6706720434,
        "start_date": "2022-02-19T12:26:09Z",
        "start_date_local": "2022-02-19T13:26:09Z",
        "timezone": "(GMT+01:00) Europe/Zurich",
        "utc_offset": 3600,
        "location_city": null,
        "location_state": null,
        "location_country": "Switzerland",
        "achievement_count": 0,
        "kudos_count": 18,
        "comment_count": 0,
        "athlete_count": 2,
        "photo_count": 0,
        "map": {
            "id": "a6706720434",
            "summary_polyline": "w{hyGg{~l@LIEIHC?FCEBAC@H^Nf@LZJAFMJBHh@CXDRAR@LDHTBPIVF`@WBIJVNPJFBEEK@IJMBOFG?ILa@DDBNLNCAHi@R`@F[LO?UNMTg@d@s@DK`@Qx@o@C@B@EEFFG?BF?GJCBG?DFBTELWXUb@UJYHKBSP_@RUV?NKl@y@P?JGBIVUH?DOZ[n@KTQ`@SL?JORMPEHUBDHQj@YPWJBLKTN`@h@NX@TTZd@GLJ^Df@`@T@VGDOJ?TJNGVQXy@DCL[f@WBJPGZFPIFHN?~@]`@HJLFTTFFPj@ZNZh@ZRVXHHNLH^h@?JPP@Hd@D\\VHTVRRZLDN^^^H\\LNHDBGD?Tb@LDFJ\\L@JTVH@DJDE?IJB@HDBBRLFf@KHJl@FVEDIBDAcAIIE]HYLGR?JKTy@HGXNDGR@VWNCRZJFFERF@HFDd@Qb@JRVRMNUPCJDDEFg@LS`Ak@PYJYh@w@NiAJIDUP]J{@N_@JABSBCBk@B??GLKAYDQAm@D?C?Oy@H_@BqBBWHMD_@LGVu@BKASRa@AO`@]NA?KBCBWCa@DMOSA[E_@KSH[GK@GM[DMEIBAAQMU@SCIDAKG?UGI@a@KKKc@BWOy@@a@IW?OG]@a@Mq@EGBOESBMCW@}@Ey@DCBWAQM[BSKQGQBIKOAKDKMk@GKMGCKg@SIUEWBg@JMp@QRHfBKpAk@r@?z@XLb@E?EVH\\~@?xAXj@Xr@n@hBjBLZA\\Kj@]z@U|@s@hAElADHBr@HLVGJBNpA`@TDF?jAJHZBb@XXf@Jl@ON?X^z@X`A^XRFAJy@~@Ch@^JEP@Jn@BBXTZLd@@`@INFRJKR|A@t@HLIb@?RbAnFChAPdCINHVEdAL~@?^LLLp@EC@I?JJ@OLF@Xv@PJ@ZCJBBC@?FVAAO@FC@DBFIH@Cl@Fr@C?E`@@VIJ?PFJEFEAB?AJC?GLBHABB^Mb@DVPGLFMJDBEBCTBRId@@PIL?LC@BBIHFj@Ip@CCBFET@FMF@l@OJKX]`@HPEXNA`@Wf@Fp@[ZCNDz@aAh@_@d@jAXUJg@LGFJH?\\UL_@ZSND?PDHHKRD?`BG`Af@XJ[ZGPTRBXNjApAVTAZOVm@LO\\YF?FIFUKJ`@JNAAQRd@n@c@JGT?JTr@ATQFMPc@E",
            "resource_state": 2
        },
        "trainer": false,
        "commute": false,
        "manual": false,
        "private": false,
        "visibility": "followers_only",
        "flagged": false,
        "gear_id": null,
        "start_latlng": [
            46.253563,
            7.536046
        ],
        "end_latlng": [
            46.22931,
            7.529442
        ],
        "average_speed": 0.981,
        "max_speed": 3.16,
        "has_heartrate": false,
        "heartrate_opt_out": false,
        "display_hide_heartrate_option": false,
        "elev_high": 2296.2,
        "elev_low": 1326.5,
        "upload_id": 7132823269,
        "upload_id_str": "7132823269",
        "external_id": "672D6CEA-7BB8-430C-9D7B-924CEE450A65-activity.fit",
        "from_accepted_tag": false,
        "pr_count": 0,
        "total_photo_count": 0,
        "has_kudoed": false
    },
    {
        "resource_state": 2,
        "athlete": {
            "id": 11730283,
            "resource_state": 1
        },
        "name": "Descente Verco",
        "distance": 4852.3,
        "moving_time": 528,
        "elapsed_time": 901,
        "total_elevation_gain": 0,
        "type": "BackcountrySki",
        "sport_type": "BackcountrySki",
        "id": 6706941227,
        "start_date": "2022-02-19T15:41:19Z",
        "start_date_local": "2022-02-19T16:41:19Z",
        "timezone": "(GMT+01:00) Europe/Zurich",
        "utc_offset": 3600,
        "location_city": null,
        "location_state": null,
        "location_country": "Switzerland",
        "achievement_count": 0,
        "kudos_count": 13,
        "comment_count": 0,
        "athlete_count": 1,
        "photo_count": 0,
        "map": {
            "id": "a6706941227",
            "summary_polyline": "{cdyG_r}l@GDDK?FC??BE@DA?C@@@EGAF?CDCAB@GL?E@@DAC@@AB?A@@CC?B?AGEBB?C?@A?DDGCFFGA@?A?F?CI@DCDBD?`@IZWF@JER_@JAp@TZD`@CLIDQEMGCGIESCw@M[I[A]o@oBQ]SWk@i@YIw@@WLa@f@s@j@KP_Ax@OR[R{@`AIDMGIBi@TOGIOOMQ@q@XQN_@j@KZIv@MTEV?XGRGHWRe@l@QLQEMQGWGs@K_CGUMKOAQJSTUPYHWNM\\Uz@[p@M|@OXKbAi@vCaBnCw@lAgArBc@~@SVYHs@CWBc@ZSDOTIXCvAG\\OVSJUBYAm@Fi@WUGQOQi@MIEMEc@@OC?@I@BC??C?@@AAFECM@KEEIIEM@OAOOQMWBUCSUO[WKYGQOG[MUSI]e@m@OMQ]g@QMiAQUWEMGAKDYWi@VKGGKK@QNa@OOJKNSJQEIIMCa@VQEUKWE_A[W[Qa@Ia@W_AG}@@]h@_Fh@qBJKLW@]AeBImCESIQAk@Ss@Eu@KSIYAq@GYOYQWM]Gc@Aa@K]C[?WIUQQGWAYMUe@WUi@k@UOSMm@?_@Mg@Bk@EYYo@UQUEWBq@Rq@BWF}AdBWJSRc@v@STc@xA_@x@QPSHY@mBW[C[BWDSPSPk@TUTUPYDq@BULOTKXE\\@bALbAAZGXWh@Qr@MRIZK|AIXMTG`@[l@Ox@MRs@`@e@IQQSKU[OGGKKEo@e@[IKKMUOIWAWG[MYSi@w@g@_@}@_Aw@YUe@KEI@GGGOE?Mc@DOUW?IJ}@?YP[No@By@GD?L",
            "resource_state": 2
        },
        "trainer": false,
        "commute": false,
        "manual": false,
        "private": false,
        "visibility": "followers_only",
        "flagged": false,
        "gear_id": null,
        "start_latlng": [
            46.229266,
            7.529447
        ],
        "end_latlng": [
            46.253726,
            7.533914
        ],
        "average_speed": 9.19,
        "max_speed": 17.04,
        "has_heartrate": false,
        "heartrate_opt_out": false,
        "display_hide_heartrate_option": false,
        "elev_high": 2302.2,
        "elev_low": 1328.1,
        "upload_id": 7133060106,
        "upload_id_str": "7133060106",
        "external_id": "7268CFCD-DCFD-4651-B36D-087CDE2F71B3-activity.fit",
        "from_accepted_tag": false,
        "pr_count": 0,
        "total_photo_count": 0,
        "has_kudoed": false
    },
    {
        "resource_state": 2,
        "athlete": {
            "id": 11730283,
            "resource_state": 1
        },
        "name": "5 K ☀️ Bois de Finges et pont du Bhoutan 200 D+",
        "distance": 5210.6,
        "moving_time": 4366,
        "elapsed_time": 7596,
        "total_elevation_gain": 203,
        "type": "Hike",
        "sport_type": "Hike",
        "id": 6726577929,
        "start_date": "2022-02-23T12:28:47Z",
        "start_date_local": "2022-02-23T13:28:47Z",
        "timezone": "(GMT+01:00) Europe/Zurich",
        "utc_offset": 3600,
        "location_city": null,
        "location_state": null,
        "location_country": "Switzerland",
        "achievement_count": 0,
        "kudos_count": 0,
        "comment_count": 0,
        "athlete_count": 1,
        "photo_count": 0,
        "map": {
            "id": "a6726577929",
            "summary_polyline": "essyGqsqm@XB@BJDd@?NHT\\`@@PG@CNAt@^XHLARKZAh@XH?RJRBjA?ZCLCNKBKJKb@QAEDETONCr@Vd@`@XBPNz@TPA\\M|@DHEDBFG\\ERKVCp@Wb@GTLTb@NHNDh@C?DN?RLRFBDx@TFJ`@ZlARr@V`@ULOPG@EHCDIJCFIb@Gj@c@^DPKRBFGH?^MDEBKLID@DIT?b@Ul@BZYDMFE`@KLMb@WVIf@g@HEj@BZOZD\\MPQFSHKNALKN[B?FUFi@Ao@DSFECEECJNLBJH@HLTRLDPDCC?CI@?@FQ^APYf@@LJDFRFv@CTFJDTDHXPFZPd@XFFP@CNZHFJPAHBVLFDAFZVT?FLPPA?BBAXJJC@DDIDHF?DNRJBPh@DLI@KDAH@TCLHl@DPIPAXF?GX@XWBI?CBADQJNBCA@@EfAaA\\SjBiBB?@DIBHE@BIAEBDCAA@@MN[Ri@h@KDk@n@_Ax@KBGWAFBAEGB?AGGMF?A@@XB?CA@EA@FBABOGH@E?BCCBB@@ACAD@AG?BCADBCG@BC@BA?BE@D??B?OINAGD?HOA?BLC@@@AHAMA@@C@DCABCED@?C?HDCCB@?GGAB?AEBHC@CCF@ECBDCABBGADCBF@K@??D@@GJIAJCEEBBACCBDABBAJCB@@ED@PKLKCGJ?EBCE?AJC@a@DMKM?G@GJK@QAEEQCG@EECDQCDFOAEFG?]FSEOSg@[U@GMKEOFEOI@Kc@SWKCGIGOIi@]c@UCEGKQ?KKa@MIQUGYGk@?YEc@IMI?IJCJ?XKf@CxAE`@?PCR?\\Jl@DhAPn@FDBXD@Dn@?^E??HGT@LCN?P@DABEEBF?RJ\\?v@ATGJQI@CEEFFABRBHLIb@El@G\\KN]Dw@Ik@Yi@H[Kc@ASM[Yi@YUUICEIwAk@KCEDQCg@DQEAIa@QS@ABBAQDAAAOAFw@CGEEMEa@GSSe@a@e@@EWWUKBIO@SKUi@_@[AEu@WQKaAMi@e@WEqAq@aAEOIKUMOa@?WJQNiALe@NEFKABEIAe@Cm@LKJo@U?COEGIYEq@e@CBg@SE@KJIBCDWNQPKDOVg@@WDo@?i@KG@c@Y]KWB_@PUMGDCIEAB?AEi@SUAQHQBQKY[OEaAG]?w@G@DCA?Ek@QYSUB]Mu@c@QM@OALB?ADBGA@",
            "resource_state": 2
        },
        "trainer": false,
        "commute": false,
        "manual": false,
        "private": true,
        "visibility": "only_me",
        "flagged": false,
        "gear_id": null,
        "start_latlng": [
            46.30851,
            7.632095
        ],
        "end_latlng": [
            46.309939,
            7.632602
        ],
        "average_speed": 1.193,
        "max_speed": 4.5,
        "has_heartrate": false,
        "heartrate_opt_out": false,
        "display_hide_heartrate_option": false,
        "elev_high": 845.7,
        "elev_low": 639.6,
        "upload_id": 7154207409,
        "upload_id_str": "7154207409",
        "external_id": "FEA8F017-BC40-4602-A703-4C2529D5F9EE-activity.fit",
        "from_accepted_tag": false,
        "pr_count": 0,
        "total_photo_count": 0,
        "has_kudoed": false
    },
    {
        "resource_state": 2,
        "athlete": {
            "id": 11730283,
            "resource_state": 1
        },
        "name": "20 K ☀️ Fruitière de Nyon 930 D+",
        "distance": 20013,
        "moving_time": 9445,
        "elapsed_time": 10377,
        "total_elevation_gain": 928,
        "type": "Run",
        "sport_type": "Run",
        "workout_type": 0,
        "id": 6735743335,
        "start_date": "2022-02-25T10:16:48Z",
        "start_date_local": "2022-02-25T11:16:48Z",
        "timezone": "(GMT+01:00) Europe/Zurich",
        "utc_offset": 3600,
        "location_city": null,
        "location_state": null,
        "location_country": "Switzerland",
        "achievement_count": 1,
        "kudos_count": 14,
        "comment_count": 0,
        "athlete_count": 3,
        "photo_count": 0,
        "map": {
            "id": "a6735743335",
            "summary_polyline": "mjmzG_~{d@~Bq@\\NB\\gAvFk@jBmEhH^xAo@vCJjCOvC]fAEjAq@jDoBjF}@fHDbEjAtFcAtAs@Gk@V[~@OxDaAzDQvAu@|Bi@fGaAnEFpFu@hDs@jAoA~@aAc@kABOnBq@~C?dDHhDQdBNxA[tA?p@Vt@hAdAZzBr@jAd@pGFvBf@bAx@bEt@lAW|Bg@jJZtDwAdIq@~HF~AS`CCbFOvBJ|Bi@~Cm@vAo@z@_AtB{CtCm@tAM~A]Xq@bCMnBVjDq@bAc@`B?zEkAvJuCBcClAu@`AyAhD[|D?tAb@vAP?h@p@b@fCYtDqC`EeAv@i@FKQ`AcBHqBGu@LQEjAJfAu@fBgB]{BdAYd@iArFkA~@_A@q@i@cAqBcB\\kCo@q@Fe@`@e@GaAuCs@XQRa@lAu@`@cDKkAfAcHhA]eF[m@kCoCmB_Ha@yCmA_C_AwFyC_E}CaCmBqB@{AQw@LaA[Hw@e@_BBo@WsD_GoC}BEy@NAGn@QNyEcB_DB]UWo@iCmKi@c@l@VIIoDa@y@HwBpAiAXcDjCa@FYI}@uAM@NF{@sAeA}@cFDiDfAmCYa@}@?gAb@kCSkEb@_AzBgAh@sAC_Aq@gDkBgEFmL`@eDa@uBLwArAg@`AcBdFa@`D_Ax@cC^_@tDj@r@Uv@cAxFqBpBaB`Bq@\\]`AqC^a@rL}Dp@o@|@iBbDZ`@STm@XoI`AoBBu@{E_My@eEM}ATcElCiDP}@Eu@_A_EPkATKAs@y@}FHsG[{BGuCU}A}AyEsC}DWwA{BiDa@cBXq@`D}CbBsC^yAOiBr@gCnBy@jAgAnDmAhCoBb@AHs@d@c@rBCbBd@bAt@o@n@Qn@F~@Kn@cCjFQxAJb@^Tq@^c@v@QnAHt@Ml@DbAxL`CdKpGjBvBp@lAtB~Av@pAnCjHd@jBSf@n@nAHk@IeCtCrA\\AFYTT`@nBRhFp@lDVZl@Z`@OQaAGgEt@iDJzBlAdBLvFf@wAbDgBdAoA~@mCT{Ap@yBJoAbEyFjDgGnBEhEz@fBp@r@|@hAYj@vARPpB{@vEbBl@a@qAeAu@qBoA[WY?c@^gBAeAkCkEsAQq@cFmA{Ci@wC}CkJB}@h@{@hAg@bAaEnAoAzBw@xEHpBfA|@FfEuClA}B`CcBlDs@lAVlBcAlAmBpCsB^eBu@?",
            "resource_state": 2
        },
        "trainer": false,
        "commute": false,
        "manual": false,
        "private": false,
        "visibility": "followers_only",
        "flagged": false,
        "gear_id": null,
        "start_latlng": [
            46.44023912027478,
            6.210407121106982
        ],
        "end_latlng": [
            46.44033718854189,
            6.210277704522014
        ],
        "average_speed": 2.119,
        "max_speed": 5.53,
        "average_cadence": 69.7,
        "average_temp": 14,
        "has_heartrate": false,
        "heartrate_opt_out": false,
        "display_hide_heartrate_option": false,
        "elev_high": 1350.2,
        "elev_low": 588.8,
        "upload_id": 7164074435,
        "upload_id_str": "7164074435",
        "external_id": "garmin_push_8356365654",
        "from_accepted_tag": false,
        "pr_count": 0,
        "total_photo_count": 0,
        "has_kudoed": false
    },
    {
        "resource_state": 2,
        "athlete": {
            "id": 11730283,
            "resource_state": 1
        },
        "name": "🎿 🦭 15 K ☀️ Cabane Brunet et pied du Mont Rogneux 1350 D+ depuis Lourtier",
        "distance": 14762.4,
        "moving_time": 9445,
        "elapsed_time": 15932,
        "total_elevation_gain": 1348.8,
        "type": "BackcountrySki",
        "sport_type": "BackcountrySki",
        "id": 6740294797,
        "start_date": "2022-02-26T07:57:01Z",
        "start_date_local": "2022-02-26T08:57:01Z",
        "timezone": "(GMT+01:00) Europe/Zurich",
        "utc_offset": 3600,
        "location_city": null,
        "location_state": null,
        "location_country": "Switzerland",
        "achievement_count": 0,
        "kudos_count": 15,
        "comment_count": 0,
        "athlete_count": 1,
        "photo_count": 0,
        "map": {
            "id": "a6740294797",
            "summary_polyline": "gq_xGo`lk@BlCg@rBVZMbADtAJPGl@pAjBQrA_@\\LdB]t@NjAUTErA\\~Bw@bA\\xADl@@tB]BGx@RhBkBbCCfAk@rCJJOKNPVo@z@_AP}AHHBjAi@nDB~Ae@REzAQ^Dt@IA~@k@Xg@p@URc@HD@t@_@`@Ip@WV?`@ML{@dELlAM`Cq@xAp@Ic@lAZ?AXe@tAj@HMb@XLEnBs@p@?bBBfBZc@VAzBtBrAtBHfAYpBDXfB?l@XD^^~@bBu@`AsCNcAdAmBnAgAf@_AZGFk@h@s@xA_AAu@z@qAZwAjAaBXgAbAi@`AyA\\}CPBb@_@tAAl@_AjD_BZsAh@k@lB{Dp@{BTmBt@qAb@o@x@s@dBQd@_@JeBr@gC@s@RYLHDjAJAx@iCZ{AGeA?}HXqAi@yCPe@|@n@HWFi@K]@c@Ta@a@}@^YPs@SkAfDlB|BxBZEf@yAZNb@g@t@hAB~Ar@d@f@pA|CbEzC|I`A|DXN|@xA@^r@?VV@VG^LZW`Av@Vz@dAb@fDt@zCt@d@ZMj@RP~ABlD\\zAbA`B\nBFvCTRPfDc@`BT|@v@|Bp@xDT\\jBtIl@bBFj@K^d@rAhAl@G^JLXJh@UPT`@nB`B^~@G~C|A`CvCdA`BXdADrACEGJPUDmAi@oB{DqGsA_As@X}@KeD}BgBSqA_BYaAPiAIk@eC_IoDcM`@mCGcCc@}D[mB}A{DcAyEcCaEq@}CuAwEUAc@cBkCkDy@kDoCaIcAeBe@So@uBwAoB?oA[McAgBmAKS]}@f@WUgBTiAYmA_Ah@^PtAUp@]@Th@@v@QrCHb@cBmA?h@h@fCSbBFf@QxDJfCQfBi@dAM|@MBAo@Us@[Tu@xDG~AKSCl@y@^u@ImC|Cm@~A{@jE_AxBiAfAa@fBcAl@gAPiArAaADgAj@c@vCqD`EWl@RLs@`@eAbC]rAg@t@_@Hq@pAyAlAMb@m@PgDrIcArAa@BFw@Yq@sCw@NoAM}A_BgDkBwAo@j@]oDJ]d@?`@c@Uc@OeARg@m@Ux@uAu@Ep@wAk@GdAoBI{Cp@eGLi@XSj@qBGQuD~BNoAC}@J_@n@c@AeBXeBDiCkCvET[n@iF`AuARgDr@sDGuH\\aF?mDUkBs@gCh@cFK?",
            "resource_state": 2
        },
        "trainer": false,
        "commute": false,
        "manual": false,
        "private": false,
        "visibility": "followers_only",
        "flagged": false,
        "gear_id": null,
        "start_latlng": [
            46.041968,
            7.275766
        ],
        "end_latlng": [
            46.042126,
            7.274982
        ],
        "average_speed": 1.563,
        "max_speed": 12.74,
        "average_cadence": 49.9,
        "average_temp": 25,
        "has_heartrate": false,
        "heartrate_opt_out": false,
        "display_hide_heartrate_option": false,
        "elev_high": 2650.6,
        "elev_low": 1310.4,
        "upload_id": 7168975666,
        "upload_id_str": "7168975666",
        "external_id": "garmin_push_8361565914",
        "from_accepted_tag": false,
        "pr_count": 0,
        "total_photo_count": 0,
        "has_kudoed": false
    }
]
